[
  {
    "id": 1,
    "timestamp": "2025-10-16T19:46:07.582687",
    "eventType": "scheduled_sync",
    "status": "completed",
    "details": {
      "push_result": {
        "status": "success",
        "message": "No pending logs",
        "processed": 0,
        "failed": 0
      },
      "pull_result": {
        "status": "success",
        "message": "No new entries",
        "pulled": 0
      },
      "sync_time": "2025-10-16T19:46:07.582687"
    }
  },
  {
    "id": 2,
    "timestamp": "2025-10-19T11:27:55.113587",
    "eventType": "scheduled_sync",
    "status": "completed",
    "details": {
      "push_result": {
        "status": "success",
        "message": "No pending logs",
        "processed": 0,
        "failed": 0
      },
      "pull_result": {
        "status": "success",
        "message": "No new entries",
        "pulled": 0
      },
      "sync_time": "2025-10-19T11:27:55.097248"
    }
  },
  {
    "id": 3,
    "timestamp": "2025-10-19T11:28:17.610146",
    "eventType": "scheduled_sync",
    "status": "completed",
    "details": {
      "push_result": {
        "status": "success",
        "message": "No pending logs",
        "processed": 0,
        "failed": 0
      },
      "pull_result": {
        "status": "success",
        "message": "No new entries",
        "pulled": 0
      },
      "sync_time": "2025-10-19T11:28:17.610146"
    }
  },
  {
    "id": 4,
    "timestamp": "2025-10-19T11:28:49.481117",
    "eventType": "scheduled_sync",
    "status": "completed",
    "details": {
      "push_result": {
        "status": "success",
        "message": "No pending logs",
        "processed": 0,
        "failed": 0
      },
      "pull_result": {
        "status": "success",
        "message": "No new entries",
        "pulled": 0
      },
      "sync_time": "2025-10-19T11:28:49.468535"
    }
  },
  {
    "id": 5,
    "timestamp": "2025-10-19T11:29:26.099875",
    "eventType": "scheduled_sync",
    "status": "completed",
    "details": {
      "push_result": {
        "status": "success",
        "message": "No pending logs",
        "processed": 0,
        "failed": 0
      },
      "pull_result": {
        "status": "success",
        "message": "No new entries",
        "pulled": 0
      },
      "sync_time": "2025-10-19T11:29:26.099875"
    }
  },
  {
    "id": 6,
    "timestamp": "2025-10-19T11:29:41.973434",
    "eventType": "scheduled_sync",
    "status": "completed",
    "details": {
      "push_result": {
        "status": "success",
        "message": "No pending logs",
        "processed": 0,
        "failed": 0
      },
      "pull_result": {
        "status": "success",
        "message": "No new entries",
        "pulled": 0
      },
      "sync_time": "2025-10-19T11:29:41.972892"
    }
  },
  {
    "id": 7,
    "timestamp": "2025-10-19T11:29:58.914652",
    "eventType": "scheduled_sync",
    "status": "completed",
    "details": {
      "push_result": {
        "status": "success",
        "message": "No pending logs",
        "processed": 0,
        "failed": 0
      },
      "pull_result": {
        "status": "success",
        "message": "No new entries",
        "pulled": 0
      },
      "sync_time": "2025-10-19T11:29:58.913638"
    }
  },
  {
    "id": 8,
    "timestamp": "2025-10-19T11:30:17.133465",
    "eventType": "scheduled_sync",
    "status": "completed",
    "details": {
      "push_result": {
        "status": "success",
        "message": "No pending logs",
        "processed": 0,
        "failed": 0
      },
      "pull_result": {
        "status": "success",
        "message": "No new entries",
        "pulled": 0
      },
      "sync_time": "2025-10-19T11:30:17.132926"
    }
  },
  {
    "id": 9,
    "timestamp": "2025-10-19T11:30:36.414430",
    "eventType": "scheduled_sync",
    "status": "completed",
    "details": {
      "push_result": {
        "status": "success",
        "message": "No pending logs",
        "processed": 0,
        "failed": 0
      },
      "pull_result": {
        "status": "success",
        "message": "No new entries",
        "pulled": 0
      },
      "sync_time": "2025-10-19T11:30:36.413878"
    }
  },
  {
    "id": 10,
    "timestamp": "2025-10-19T11:30:55.599101",
    "eventType": "scheduled_sync",
    "status": "completed",
    "details": {
      "push_result": {
        "status": "success",
        "message": "No pending logs",
        "processed": 0,
        "failed": 0
      },
      "pull_result": {
        "status": "success",
        "message": "No new entries",
        "pulled": 0
      },
      "sync_time": "2025-10-19T11:30:55.598563"
    }
  },
  {
    "id": 11,
    "timestamp": "2025-10-19T11:31:14.516503",
    "eventType": "scheduled_sync",
    "status": "completed",
    "details": {
      "push_result": {
        "status": "success",
        "message": "No pending logs",
        "processed": 0,
        "failed": 0
      },
      "pull_result": {
        "status": "success",
        "message": "No new entries",
        "pulled": 0
      },
      "sync_time": "2025-10-19T11:31:14.515971"
    }
  },
  {
    "id": 12,
    "timestamp": "2025-10-19T11:31:34.054453",
    "eventType": "scheduled_sync",
    "status": "completed",
    "details": {
      "push_result": {
        "status": "success",
        "message": "No pending logs",
        "processed": 0,
        "failed": 0
      },
      "pull_result": {
        "status": "success",
        "message": "No new entries",
        "pulled": 0
      },
      "sync_time": "2025-10-19T11:31:34.052433"
    }
  },
  {
    "id": 13,
    "timestamp": "2025-10-19T11:31:51.980956",
    "eventType": "scheduled_sync",
    "status": "completed",
    "details": {
      "push_result": {
        "status": "success",
        "message": "No pending logs",
        "processed": 0,
        "failed": 0
      },
      "pull_result": {
        "status": "success",
        "message": "No new entries",
        "pulled": 0
      },
      "sync_time": "2025-10-19T11:31:51.980956"
    }
  },
  {
    "id": 14,
    "timestamp": "2025-10-19T11:32:11.389571",
    "eventType": "scheduled_sync",
    "status": "completed",
    "details": {
      "push_result": {
        "status": "success",
        "message": "No pending logs",
        "processed": 0,
        "failed": 0
      },
      "pull_result": {
        "status": "success",
        "message": "No new entries",
        "pulled": 0
      },
      "sync_time": "2025-10-19T11:32:11.389571"
    }
  },
  {
    "id": 15,
    "timestamp": "2025-10-19T11:32:32.689179",
    "eventType": "scheduled_sync",
    "status": "completed",
    "details": {
      "push_result": {
        "status": "success",
        "message": "No pending logs",
        "processed": 0,
        "failed": 0
      },
      "pull_result": {
        "status": "success",
        "message": "No new entries",
        "pulled": 0
      },
      "sync_time": "2025-10-19T11:32:32.689179"
    }
  },
  {
    "id": 16,
    "timestamp": "2025-10-19T11:32:50.666925",
    "eventType": "scheduled_sync",
    "status": "completed",
    "details": {
      "push_result": {
        "status": "success",
        "message": "No pending logs",
        "processed": 0,
        "failed": 0
      },
      "pull_result": {
        "status": "success",
        "message": "No new entries",
        "pulled": 0
      },
      "sync_time": "2025-10-19T11:32:50.664904"
    }
  },
  {
    "id": 17,
    "timestamp": "2025-10-19T11:33:12.543032",
    "eventType": "scheduled_sync",
    "status": "completed",
    "details": {
      "push_result": {
        "status": "success",
        "message": "No pending logs",
        "processed": 0,
        "failed": 0
      },
      "pull_result": {
        "status": "success",
        "message": "No new entries",
        "pulled": 0
      },
      "sync_time": "2025-10-19T11:33:12.541423"
    }
  },
  {
    "id": 18,
    "timestamp": "2025-10-19T11:33:32.065382",
    "eventType": "scheduled_sync",
    "status": "completed",
    "details": {
      "push_result": {
        "status": "success",
        "message": "No pending logs",
        "processed": 0,
        "failed": 0
      },
      "pull_result": {
        "status": "success",
        "message": "No new entries",
        "pulled": 0
      },
      "sync_time": "2025-10-19T11:33:32.064840"
    }
  },
  {
    "id": 19,
    "timestamp": "2025-10-19T11:33:56.254765",
    "eventType": "scheduled_sync",
    "status": "completed",
    "details": {
      "push_result": {
        "status": "success",
        "message": "No pending logs",
        "processed": 0,
        "failed": 0
      },
      "pull_result": {
        "status": "success",
        "message": "No new entries",
        "pulled": 0
      },
      "sync_time": "2025-10-19T11:33:56.254765"
    }
  },
  {
    "id": 20,
    "timestamp": "2025-10-19T11:34:17.569746",
    "eventType": "scheduled_sync",
    "status": "completed",
    "details": {
      "push_result": {
        "status": "success",
        "message": "No pending logs",
        "processed": 0,
        "failed": 0
      },
      "pull_result": {
        "status": "success",
        "message": "No new entries",
        "pulled": 0
      },
      "sync_time": "2025-10-19T11:34:17.569746"
    }
  },
  {
    "id": 21,
    "timestamp": "2025-10-19T11:34:36.056580",
    "eventType": "scheduled_sync",
    "status": "completed",
    "details": {
      "push_result": {
        "status": "success",
        "message": "No pending logs",
        "processed": 0,
        "failed": 0
      },
      "pull_result": {
        "status": "success",
        "message": "No new entries",
        "pulled": 0
      },
      "sync_time": "2025-10-19T11:34:36.055721"
    }
  },
  {
    "id": 22,
    "timestamp": "2025-10-19T11:34:56.164315",
    "eventType": "scheduled_sync",
    "status": "completed",
    "details": {
      "push_result": {
        "status": "success",
        "message": "No pending logs",
        "processed": 0,
        "failed": 0
      },
      "pull_result": {
        "status": "success",
        "message": "No new entries",
        "pulled": 0
      },
      "sync_time": "2025-10-19T11:34:56.164315"
    }
  },
  {
    "id": 23,
    "timestamp": "2025-10-19T11:35:16.228518",
    "eventType": "scheduled_sync",
    "status": "completed",
    "details": {
      "push_result": {
        "status": "success",
        "message": "No pending logs",
        "processed": 0,
        "failed": 0
      },
      "pull_result": {
        "status": "success",
        "message": "No new entries",
        "pulled": 0
      },
      "sync_time": "2025-10-19T11:35:16.227950"
    }
  },
  {
    "id": 24,
    "timestamp": "2025-10-19T11:35:34.974998",
    "eventType": "scheduled_sync",
    "status": "completed",
    "details": {
      "push_result": {
        "status": "success",
        "message": "No pending logs",
        "processed": 0,
        "failed": 0
      },
      "pull_result": {
        "status": "success",
        "message": "No new entries",
        "pulled": 0
      },
      "sync_time": "2025-10-19T11:35:34.974998"
    }
  },
  {
    "id": 25,
    "timestamp": "2025-10-19T11:35:51.977959",
    "eventType": "scheduled_sync",
    "status": "completed",
    "details": {
      "push_result": {
        "status": "success",
        "message": "No pending logs",
        "processed": 0,
        "failed": 0
      },
      "pull_result": {
        "status": "success",
        "message": "No new entries",
        "pulled": 0
      },
      "sync_time": "2025-10-19T11:35:51.975948"
    }
  },
  {
    "id": 26,
    "timestamp": "2025-10-19T11:36:09.129994",
    "eventType": "scheduled_sync",
    "status": "completed",
    "details": {
      "push_result": {
        "status": "success",
        "message": "No pending logs",
        "processed": 0,
        "failed": 0
      },
      "pull_result": {
        "status": "success",
        "message": "No new entries",
        "pulled": 0
      },
      "sync_time": "2025-10-19T11:36:09.129994"
    }
  },
  {
    "id": 27,
    "timestamp": "2025-10-19T11:36:26.017611",
    "eventType": "scheduled_sync",
    "status": "completed",
    "details": {
      "push_result": {
        "status": "success",
        "message": "No pending logs",
        "processed": 0,
        "failed": 0
      },
      "pull_result": {
        "status": "success",
        "message": "No new entries",
        "pulled": 0
      },
      "sync_time": "2025-10-19T11:36:26.017611"
    }
  },
  {
    "id": 28,
    "timestamp": "2025-10-19T11:36:43.499085",
    "eventType": "scheduled_sync",
    "status": "completed",
    "details": {
      "push_result": {
        "status": "success",
        "message": "No pending logs",
        "processed": 0,
        "failed": 0
      },
      "pull_result": {
        "status": "success",
        "message": "No new entries",
        "pulled": 0
      },
      "sync_time": "2025-10-19T11:36:43.499085"
    }
  },
  {
    "id": 29,
    "timestamp": "2025-10-19T11:37:00.080412",
    "eventType": "scheduled_sync",
    "status": "completed",
    "details": {
      "push_result": {
        "status": "success",
        "message": "No pending logs",
        "processed": 0,
        "failed": 0
      },
      "pull_result": {
        "status": "success",
        "message": "No new entries",
        "pulled": 0
      },
      "sync_time": "2025-10-19T11:37:00.080412"
    }
  },
  {
    "id": 30,
    "timestamp": "2025-10-19T11:37:17.215239",
    "eventType": "scheduled_sync",
    "status": "completed",
    "details": {
      "push_result": {
        "status": "success",
        "message": "No pending logs",
        "processed": 0,
        "failed": 0
      },
      "pull_result": {
        "status": "success",
        "message": "No new entries",
        "pulled": 0
      },
      "sync_time": "2025-10-19T11:37:17.214731"
    }
  },
  {
    "id": 31,
    "timestamp": "2025-10-19T11:37:36.890153",
    "eventType": "scheduled_sync",
    "status": "completed",
    "details": {
      "push_result": {
        "status": "success",
        "message": "No pending logs",
        "processed": 0,
        "failed": 0
      },
      "pull_result": {
        "status": "success",
        "message": "No new entries",
        "pulled": 0
      },
      "sync_time": "2025-10-19T11:37:36.890153"
    }
  },
  {
    "id": 32,
    "timestamp": "2025-10-19T11:37:56.021394",
    "eventType": "scheduled_sync",
    "status": "completed",
    "details": {
      "push_result": {
        "status": "success",
        "message": "No pending logs",
        "processed": 0,
        "failed": 0
      },
      "pull_result": {
        "status": "success",
        "message": "No new entries",
        "pulled": 0
      },
      "sync_time": "2025-10-19T11:37:56.020832"
    }
  },
  {
    "id": 33,
    "timestamp": "2025-10-19T11:38:15.180740",
    "eventType": "scheduled_sync",
    "status": "completed",
    "details": {
      "push_result": {
        "status": "success",
        "message": "No pending logs",
        "processed": 0,
        "failed": 0
      },
      "pull_result": {
        "status": "success",
        "message": "No new entries",
        "pulled": 0
      },
      "sync_time": "2025-10-19T11:38:15.170546"
    }
  },
  {
    "id": 34,
    "timestamp": "2025-10-19T11:38:33.514856",
    "eventType": "scheduled_sync",
    "status": "completed",
    "details": {
      "push_result": {
        "status": "success",
        "message": "No pending logs",
        "processed": 0,
        "failed": 0
      },
      "pull_result": {
        "status": "success",
        "message": "No new entries",
        "pulled": 0
      },
      "sync_time": "2025-10-19T11:38:33.514856"
    }
  },
  {
    "id": 35,
    "timestamp": "2025-10-19T11:38:53.521519",
    "eventType": "scheduled_sync",
    "status": "completed",
    "details": {
      "push_result": {
        "status": "success",
        "message": "No pending logs",
        "processed": 0,
        "failed": 0
      },
      "pull_result": {
        "status": "success",
        "message": "No new entries",
        "pulled": 0
      },
      "sync_time": "2025-10-19T11:38:53.521519"
    }
  },
  {
    "id": 36,
    "timestamp": "2025-10-19T11:39:11.324295",
    "eventType": "scheduled_sync",
    "status": "completed",
    "details": {
      "push_result": {
        "status": "success",
        "message": "No pending logs",
        "processed": 0,
        "failed": 0
      },
      "pull_result": {
        "status": "success",
        "message": "No new entries",
        "pulled": 0
      },
      "sync_time": "2025-10-19T11:39:11.324295"
    }
  },
  {
    "id": 37,
    "timestamp": "2025-10-19T11:39:29.800984",
    "eventType": "scheduled_sync",
    "status": "completed",
    "details": {
      "push_result": {
        "status": "success",
        "message": "No pending logs",
        "processed": 0,
        "failed": 0
      },
      "pull_result": {
        "status": "success",
        "message": "No new entries",
        "pulled": 0
      },
      "sync_time": "2025-10-19T11:39:29.800984"
    }
  },
  {
    "id": 38,
    "timestamp": "2025-10-19T11:39:48.261935",
    "eventType": "scheduled_sync",
    "status": "completed",
    "details": {
      "push_result": {
        "status": "success",
        "message": "No pending logs",
        "processed": 0,
        "failed": 0
      },
      "pull_result": {
        "status": "success",
        "message": "No new entries",
        "pulled": 0
      },
      "sync_time": "2025-10-19T11:39:48.261388"
    }
  },
  {
    "id": 39,
    "timestamp": "2025-10-19T11:40:07.132953",
    "eventType": "scheduled_sync",
    "status": "completed",
    "details": {
      "push_result": {
        "status": "success",
        "message": "No pending logs",
        "processed": 0,
        "failed": 0
      },
      "pull_result": {
        "status": "success",
        "message": "No new entries",
        "pulled": 0
      },
      "sync_time": "2025-10-19T11:40:07.132446"
    }
  },
  {
    "id": 40,
    "timestamp": "2025-10-19T11:40:25.936434",
    "eventType": "scheduled_sync",
    "status": "completed",
    "details": {
      "push_result": {
        "status": "success",
        "message": "No pending logs",
        "processed": 0,
        "failed": 0
      },
      "pull_result": {
        "status": "success",
        "message": "No new entries",
        "pulled": 0
      },
      "sync_time": "2025-10-19T11:40:25.935460"
    }
  },
  {
    "id": 41,
    "timestamp": "2025-10-19T11:40:44.508129",
    "eventType": "scheduled_sync",
    "status": "completed",
    "details": {
      "push_result": {
        "status": "success",
        "message": "No pending logs",
        "processed": 0,
        "failed": 0
      },
      "pull_result": {
        "status": "success",
        "message": "No new entries",
        "pulled": 0
      },
      "sync_time": "2025-10-19T11:40:44.508129"
    }
  },
  {
    "id": 42,
    "timestamp": "2025-10-19T11:41:08.999100",
    "eventType": "scheduled_sync",
    "status": "completed",
    "details": {
      "push_result": {
        "status": "success",
        "message": "No pending logs",
        "processed": 0,
        "failed": 0
      },
      "pull_result": {
        "status": "success",
        "message": "No new entries",
        "pulled": 0
      },
      "sync_time": "2025-10-19T11:41:08.999100"
    }
  },
  {
    "id": 43,
    "timestamp": "2025-10-19T11:49:57.281146",
    "eventType": "scheduled_sync",
    "status": "completed",
    "details": {
      "push_result": {
        "status": "success",
        "message": "No pending logs",
        "processed": 0,
        "failed": 0
      },
      "pull_result": {
        "status": "success",
        "message": "No new entries",
        "pulled": 0
      },
      "sync_time": "2025-10-19T11:49:57.281146"
    }
  }
]