[
  {
    "id": 1,
    "sync_time": "2026-02-16T11:51:59.758819",
    "table_name": "Bills",
    "change_type": "DELETE",
    "record_id": "BILL-314f8525ae6e",
    "change_data": {
      "id": "BILL-314f8525ae6e"
    },
    "status": "pending",
    "retry_count": 0,
    "last_retry": null,
    "error_message": null,
    "created_at": "2026-02-16T11:51:59.758835"
  },
  {
    "id": 2,
    "sync_time": "2026-02-16T11:52:00.081886",
    "table_name": "Bills",
    "change_type": "DELETE",
    "record_id": "BILL-190461665a81",
    "change_data": {
      "id": "BILL-190461665a81"
    },
    "status": "pending",
    "retry_count": 0,
    "last_retry": null,
    "error_message": null,
    "created_at": "2026-02-16T11:52:00.081901"
  },
  {
    "id": 3,
    "sync_time": "2026-02-16T11:52:00.148603",
    "table_name": "Bills",
    "change_type": "DELETE",
    "record_id": "BILL-792f4cb84320",
    "change_data": {
      "id": "BILL-792f4cb84320"
    },
    "status": "pending",
    "retry_count": 0,
    "last_retry": null,
    "error_message": null,
    "created_at": "2026-02-16T11:52:00.148622"
  },
  {
    "id": 4,
    "sync_time": "2026-02-16T11:52:00.315074",
    "table_name": "Bills",
    "change_type": "DELETE",
    "record_id": "BILL-85cce7cf3492",
    "change_data": {
      "id": "BILL-85cce7cf3492"
    },
    "status": "pending",
    "retry_count": 0,
    "last_retry": null,
    "error_message": null,
    "created_at": "2026-02-16T11:52:00.315092"
  },
  {
    "id": 5,
    "sync_time": "2026-02-16T11:52:00.379908",
    "table_name": "Bills",
    "change_type": "DELETE",
    "record_id": "BILL-789ef4b18a10",
    "change_data": {
      "id": "BILL-789ef4b18a10"
    },
    "status": "pending",
    "retry_count": 0,
    "last_retry": null,
    "error_message": null,
    "created_at": "2026-02-16T11:52:00.379925"
  },
  {
    "id": 6,
    "sync_time": "2026-02-16T11:52:00.564297",
    "table_name": "Bills",
    "change_type": "DELETE",
    "record_id": "BILL-ddcbfe543189",
    "change_data": {
      "id": "BILL-ddcbfe543189"
    },
    "status": "pending",
    "retry_count": 0,
    "last_retry": null,
    "error_message": null,
    "created_at": "2026-02-16T11:52:00.564315"
  },
  {
    "id": 7,
    "sync_time": "2026-02-16T11:52:00.792499",
    "table_name": "Bills",
    "change_type": "DELETE",
    "record_id": "BILL-bae07024958b",
    "change_data": {
      "id": "BILL-bae07024958b"
    },
    "status": "pending",
    "retry_count": 0,
    "last_retry": null,
    "error_message": null,
    "created_at": "2026-02-16T11:52:00.792515"
  },
  {
    "id": 8,
    "sync_time": "2026-02-16T11:52:01.009780",
    "table_name": "Bills",
    "change_type": "DELETE",
    "record_id": "BILL-81b29f5547d4",
    "change_data": {
      "id": "BILL-81b29f5547d4"
    },
    "status": "pending",
    "retry_count": 0,
    "last_retry": null,
    "error_message": null,
    "created_at": "2026-02-16T11:52:01.009798"
  },
  {
    "id": 9,
    "sync_time": "2026-02-16T11:52:01.055646",
    "table_name": "Bills",
    "change_type": "DELETE",
    "record_id": "BILL-58bfa5369583",
    "change_data": {
      "id": "BILL-58bfa5369583"
    },
    "status": "pending",
    "retry_count": 0,
    "last_retry": null,
    "error_message": null,
    "created_at": "2026-02-16T11:52:01.055663"
  },
  {
    "id": 10,
    "sync_time": "2026-02-16T11:52:01.061150",
    "table_name": "Bills",
    "change_type": "DELETE",
    "record_id": "BILL-f6cb2d8c5962",
    "change_data": {
      "id": "BILL-f6cb2d8c5962"
    },
    "status": "pending",
    "retry_count": 0,
    "last_retry": null,
    "error_message": null,
    "created_at": "2026-02-16T11:52:01.061205"
  },
  {
    "id": 11,
    "sync_time": "2026-02-16T11:52:01.067524",
    "table_name": "Bills",
    "change_type": "DELETE",
    "record_id": "BILL-819d2d2b7fe8",
    "change_data": {
      "id": "BILL-819d2d2b7fe8"
    },
    "status": "pending",
    "retry_count": 0,
    "last_retry": null,
    "error_message": null,
    "created_at": "2026-02-16T11:52:01.067570"
  },
  {
    "id": 12,
    "sync_time": "2026-02-16T11:52:01.245091",
    "table_name": "Bills",
    "change_type": "DELETE",
    "record_id": "BILL-0e80680f4f90",
    "change_data": {
      "id": "BILL-0e80680f4f90"
    },
    "status": "pending",
    "retry_count": 0,
    "last_retry": null,
    "error_message": null,
    "created_at": "2026-02-16T11:52:01.245108"
  },
  {
    "id": 13,
    "sync_time": "2026-02-16T11:52:01.276280",
    "table_name": "Bills",
    "change_type": "DELETE",
    "record_id": "BILL-3f046bb9f29b",
    "change_data": {
      "id": "BILL-3f046bb9f29b"
    },
    "status": "pending",
    "retry_count": 0,
    "last_retry": null,
    "error_message": null,
    "created_at": "2026-02-16T11:52:01.276297"
  },
  {
    "id": 14,
    "sync_time": "2026-02-16T11:52:01.459140",
    "table_name": "Bills",
    "change_type": "DELETE",
    "record_id": "BILL-ba7e516816bd",
    "change_data": {
      "id": "BILL-ba7e516816bd"
    },
    "status": "pending",
    "retry_count": 0,
    "last_retry": null,
    "error_message": null,
    "created_at": "2026-02-16T11:52:01.459160"
  },
  {
    "id": 15,
    "sync_time": "2026-02-16T11:52:01.463416",
    "table_name": "Bills",
    "change_type": "DELETE",
    "record_id": "BILL-06c86b8c0b6b",
    "change_data": {
      "id": "BILL-06c86b8c0b6b"
    },
    "status": "pending",
    "retry_count": 0,
    "last_retry": null,
    "error_message": null,
    "created_at": "2026-02-16T11:52:01.463428"
  }
]