[
  {
    "id": "store3",
    "name": "SIRI ART JEWELLERY - Mall",
    "address": "789 Mall Complex, City",
    "phone": null,
    "status": "active",
    "createdat": null,
    "updatedat": null
  },
  {
    "id": "STR-1764574507863",
    "name": "dress cricle ",
    "address": "this is a testing store ",
    "phone": "",
    "status": "active",
    "createdat": "2025-12-01T13:05:07.863375",
    "updatedat": "2025-12-01T13:05:07.863375"
  },
  {
    "id": "STR-1764438854928",
    "name": "testing",
    "address": "testing testing ",
    "phone": "",
    "status": "active",
    "createdat": "2025-11-29T23:24:14.928058",
    "updatedat": "2025-11-29T23:24:14.928058"
  }
]